talisker/__init__.py
talisker/__main__.py
talisker/celery.py
talisker/config.py
talisker/context.py
talisker/django.py
talisker/endpoints.py
talisker/flask.py
talisker/gunicorn.py
talisker/logs.py
talisker/metrics.py
talisker/postgresql.py
talisker/prometheus.py
talisker/render.py
talisker/requests.py
talisker/sentry.py
talisker/statsd.py
talisker/testing.py
talisker/util.py
talisker/wsgi.py
talisker/logstash/talisker.filter
talisker/logstash/talisker.pattern
talisker-0.22.0.dist-info/licenses/AUTHORS.rst
talisker-0.22.0.dist-info/licenses/LICENSE
talisker-0.22.0.dist-info/METADATA
talisker-0.22.0.dist-info/WHEEL
talisker-0.22.0.dist-info/entry_points.txt
talisker-0.22.0.dist-info/top_level.txt
talisker-0.22.0.dist-info/RECORD
