Metadata-Version: 2.4
Name: talisker
Version: 0.22.0
Summary: A common WSGI stack
Home-page: https://github.com/canonical-ols/talisker
Author: Simon Davy
Author-email: simon.davy@canonical.com
Keywords: talisker
Classifier: License :: OSI Approved :: Apache Software License
Classifier: Development Status :: 4 - Beta
Classifier: Intended Audience :: Developers
Classifier: Natural Language :: English
Classifier: Topic :: Internet :: WWW/HTTP :: WSGI
Classifier: Topic :: Internet :: WWW/HTTP :: WSGI :: Middleware
Classifier: Topic :: System :: Logging
Classifier: Programming Language :: Python :: 3.5
Classifier: Programming Language :: Python :: 3.6
Classifier: Programming Language :: Python :: 3.8
Classifier: Programming Language :: Python :: 3.10
Classifier: Programming Language :: Python :: 3.12
Classifier: Programming Language :: Python :: Implementation :: CPython
License-File: LICENSE
License-File: AUTHORS.rst
Requires-Dist: Werkzeug~=1.0; python_version ~= "3.5.0"
Requires-Dist: Werkzeug<4; python_version >= "3.6"
Requires-Dist: statsd~=3.3; python_version ~= "3.5.0"
Requires-Dist: statsd<5; python_version >= "3.6"
Requires-Dist: requests~=2.25; python_version ~= "3.5.0"
Requires-Dist: requests<3.0; python_version > "3.5"
Requires-Dist: contextvars~=2.4; python_version >= "3.5" and python_version < "3.7"
Provides-Extra: asyncio
Requires-Dist: aiocontextvars==0.2.2; (python_version >= "3.5.3" and python_version < "3.7") and extra == "asyncio"
Provides-Extra: celery
Requires-Dist: celery~=4.4; python_version ~= "3.5.0" and extra == "celery"
Requires-Dist: celery>=4; python_version > "3.5" and extra == "celery"
Provides-Extra: dev
Requires-Dist: logging_tree>=1.9; extra == "dev"
Requires-Dist: pygments>=2.11; extra == "dev"
Requires-Dist: psutil>=5.9; extra == "dev"
Requires-Dist: objgraph>=3.5; extra == "dev"
Provides-Extra: django
Requires-Dist: django~=2.2; python_version ~= "3.5.0" and extra == "django"
Requires-Dist: django<5; python_version > "3.5" and extra == "django"
Provides-Extra: flask
Requires-Dist: flask~=1.1; python_version ~= "3.5.0" and extra == "flask"
Requires-Dist: flask<4; python_version > "3.5" and extra == "flask"
Requires-Dist: blinker~=1.5; python_version ~= "3.5.0" and extra == "flask"
Requires-Dist: blinker<2; python_version > "3.5" and extra == "flask"
Provides-Extra: gevent
Requires-Dist: gevent>=20.9.0; extra == "gevent"
Provides-Extra: gunicorn
Requires-Dist: gunicorn>=19.7.0; python_version > "3.6" and extra == "gunicorn"
Requires-Dist: gunicorn<21.0,>=19.7.0; (python_version >= "3.5" and python_version < "3.8") and extra == "gunicorn"
Provides-Extra: pg
Requires-Dist: sqlparse>=0.4.2; extra == "pg"
Requires-Dist: psycopg2<3.0,>=2.8; extra == "pg"
Provides-Extra: prometheus
Requires-Dist: prometheus-client~=0.7.0; python_version ~= "3.5.0" and extra == "prometheus"
Requires-Dist: prometheus-client<0.8; python_version > "3.5" and extra == "prometheus"
Provides-Extra: raven
Requires-Dist: raven>=6.4.0; extra == "raven"
Dynamic: author
Dynamic: author-email
Dynamic: classifier
Dynamic: description
Dynamic: home-page
Dynamic: keywords
Dynamic: license-file
Dynamic: provides-extra
Dynamic: requires-dist
Dynamic: summary
